RobokitRS/RobokitRS.py
RobokitRS/RobokitRS_config.py
RobokitRS/__init__.py
RobokitRS/pins/pins.config
RobokitRS-1.0.1.30.dist-info/METADATA
RobokitRS-1.0.1.30.dist-info/WHEEL
RobokitRS-1.0.1.30.dist-info/top_level.txt
RobokitRS-1.0.1.30.dist-info/RECORD
